stateset_acp_native-1.0.0.dist-info/METADATA
stateset_acp_native-1.0.0.dist-info/WHEEL
stateset_acp_native/__init__.py
stateset_acp_native/stateset_acp_native.cpython-38-x86_64-linux-gnu.so
stateset_acp_native-1.0.0.dist-info/RECORD
