Metadata-Version: 2.4
Name: stateset-acp-native
Version: 1.0.0
Classifier: Development Status :: 4 - Beta
Classifier: Intended Audience :: Developers
Classifier: License :: OSI Approved :: MIT License
Classifier: Programming Language :: Python :: 3
Classifier: Programming Language :: Python :: 3.9
Classifier: Programming Language :: Python :: 3.10
Classifier: Programming Language :: Python :: 3.11
Classifier: Programming Language :: Python :: 3.12
Classifier: Programming Language :: Rust
Summary: Native Python bindings for StateSet ACP Handler (PyO3)
Keywords: stateset,acp,native,rust,pyo3,checkout
Author-email: StateSet <support@stateset.io>
License: MIT
Requires-Python: >=3.9
Project-URL: Homepage, https://github.com/stateset/stateset-acp-handler
Project-URL: Repository, https://github.com/stateset/stateset-acp-handler
